{
  "brand": "Toyota",
  "year": 2025,
  "vehicles": [
    {
      "model": "4Runner",
      "trim": "Limited",
      "tires": [
        {
          "size": "265/55R20"
        }
      ]
    },
    {
      "model": "4Runner",
      "trim": "Platinum",
      "tires": [
        {
          "size": "265/55R20"
        }
      ]
    },
    {
      "model": "4Runner",
      "trim": "SR5",
      "tires": [
        {
          "size": "245/70R17"
        }
      ]
    },
    {
      "model": "4Runner",
      "trim": "TRD Off-Road Premium",
      "tires": [
        {
          "size": "265/70R18"
        }
      ]
    },
    {
      "model": "4Runner",
      "trim": "TRD Off-Road Premium i-FORCE MAX",
      "tires": [
        {
          "size": "265/70R18"
        }
      ]
    },
    {
      "model": "4Runner",
      "trim": "TRD Pro",
      "tires": [
        {
          "size": "265/70R18"
        }
      ]
    },
    {
      "model": "4Runner",
      "trim": "TRD Sport",
      "tires": [
        {
          "size": "265/55R20"
        }
      ]
    },
    {
      "model": "4Runner",
      "trim": "Trailhunter",
      "tires": [
        {
          "size": "265/70R18"
        }
      ]
    },
    {
      "model": "Camry",
      "trim": "Hybrid SE (AWD)",
      "tires": [
        {
          "size": "205/65R16"
        },
        {
          "size": "235/45R18"
        }
      ]
    },
    {
      "model": "Camry",
      "trim": "Hybrid SE (FWD)",
      "tires": [
        {
          "size": "205/65R16"
        },
        {
          "size": "235/45R18"
        }
      ]
    },
    {
      "model": "Camry",
      "trim": "Hybrid XLE",
      "tires": [
        {
          "size": "235/45R18"
        }
      ]
    },
    {
      "model": "Camry",
      "trim": "Hybrid XSE",
      "tires": [
        {
          "size": "235/40R19"
        }
      ]
    },
    {
      "model": "Corolla",
      "trim": "CVT Hatchback",
      "tires": [
        {
          "size": "195/65R15"
        }
      ]
    },
    {
      "model": "Corolla",
      "trim": "Cross Hybrid SE",
      "tires": [
        {
          "size": "215/65R17"
        }
      ]
    },
    {
      "model": "Corolla",
      "trim": "Cross Hybrid XSE",
      "tires": [
        {
          "size": "225/55R18"
        }
      ]
    },
    {
      "model": "Corolla",
      "trim": "Cross L (AWD)",
      "tires": [
        {
          "size": "215/65R17"
        }
      ]
    },
    {
      "model": "Corolla",
      "trim": "Cross L (FWD)",
      "tires": [
        {
          "size": "215/65R17"
        }
      ]
    },
    {
      "model": "Corolla",
      "trim": "Cross LE (AWD)",
      "tires": [
        {
          "size": "215/65R17"
        }
      ]
    },
    {
      "model": "Corolla",
      "trim": "Cross LE (FWD)",
      "tires": [
        {
          "size": "215/65R17"
        }
      ]
    },
    {
      "model": "Corolla",
      "trim": "Cross XLE (AWD)",
      "tires": [
        {
          "size": "225/55R18"
        }
      ]
    },
    {
      "model": "Corolla",
      "trim": "Hybrid LE",
      "tires": [
        {
          "size": "195/65R15"
        }
      ]
    },
    {
      "model": "Corolla",
      "trim": "Hybrid SE",
      "tires": [
        {
          "size": "225/40R18"
        }
      ]
    },
    {
      "model": "Corolla",
      "trim": "Hybrid XSE",
      "tires": [
        {
          "size": "205/55R16"
        }
      ]
    },
    {
      "model": "Corolla",
      "trim": "L",
      "tires": [
        {
          "size": "195/65R15"
        }
      ]
    },
    {
      "model": "Corolla",
      "trim": "LE",
      "tires": [
        {
          "size": "205/55R16"
        }
      ]
    },
    {
      "model": "Corolla",
      "trim": "SE",
      "tires": [
        {
          "size": "225/40R18"
        },
        {
          "size": "205/55R16"
        }
      ]
    },
    {
      "model": "Corolla",
      "trim": "SE Plus Hatchback",
      "tires": [
        {
          "size": "205/55R16"
        }
      ]
    },
    {
      "model": "Corolla",
      "trim": "SE Upgrade Hatchback",
      "tires": [
        {
          "size": "225/40R18"
        }
      ]
    },
    {
      "model": "Corolla",
      "trim": "XSE Hatchback",
      "tires": [
        {
          "size": "225/40R18"
        }
      ]
    },
    {
      "model": "Crown",
      "trim": "Limited",
      "tires": [
        {
          "size": "225/55R19"
        }
      ]
    },
    {
      "model": "Crown",
      "trim": "Platinum",
      "tires": [
        {
          "size": "225/45R21"
        }
      ]
    },
    {
      "model": "Crown",
      "trim": "Signia Limited",
      "tires": [
        {
          "size": "235/45R21"
        }
      ]
    },
    {
      "model": "GR",
      "trim": "Corolla Core",
      "tires": [
        {
          "size": "235/40R18"
        }
      ]
    },
    {
      "model": "GR",
      "trim": "Corolla Premium",
      "tires": [
        {
          "size": "235/40R18"
        }
      ]
    },
    {
      "model": "GR",
      "trim": "Supra Premium",
      "tires": [
        {
          "size": "255/35R19"
        },
        {
          "size": "275/35R19"
        }
      ]
    },
    {
      "model": "GR86",
      "trim": "Base",
      "tires": [
        {
          "size": "215/45R17"
        }
      ]
    },
    {
      "model": "GR86",
      "trim": "Hakone Special Edition",
      "tires": [
        {
          "size": "215/40R18"
        }
      ]
    },
    {
      "model": "GR86",
      "trim": "Premium",
      "tires": [
        {
          "size": "215/40R18"
        }
      ]
    },
    {
      "model": "Grand",
      "trim": "Highlander Hybrid Limited",
      "tires": [
        {
          "size": "255/55R20"
        }
      ]
    },
    {
      "model": "Grand",
      "trim": "Highlander Hybrid MAX Platinum",
      "tires": [
        {
          "size": "255/55R20"
        }
      ]
    },
    {
      "model": "Grand",
      "trim": "Highlander Hybrid XLE",
      "tires": [
        {
          "size": "255/65R18"
        }
      ]
    },
    {
      "model": "Grand",
      "trim": "Highlander Limited",
      "tires": [
        {
          "size": "255/55R20"
        }
      ]
    },
    {
      "model": "Grand",
      "trim": "Highlander XLE",
      "tires": [
        {
          "size": "255/65R18"
        }
      ]
    },
    {
      "model": "Highlander",
      "trim": "Hybrid LE",
      "tires": [
        {
          "size": "235/65R18"
        }
      ]
    },
    {
      "model": "Highlander",
      "trim": "Hybrid Limited",
      "tires": [
        {
          "size": "235/55R20"
        }
      ]
    },
    {
      "model": "Highlander",
      "trim": "Hybrid XLE",
      "tires": [
        {
          "size": "235/65R18"
        }
      ]
    },
    {
      "model": "Highlander",
      "trim": "Limited",
      "tires": [
        {
          "size": "235/55R20"
        }
      ]
    },
    {
      "model": "Highlander",
      "trim": "XLE",
      "tires": [
        {
          "size": "235/65R18"
        }
      ]
    },
    {
      "model": "Highlander",
      "trim": "XSE",
      "tires": [
        {
          "size": "235/55R20"
        }
      ]
    },
    {
      "model": "Land",
      "trim": "Cruiser 1958",
      "tires": [
        {
          "size": "245/70R18"
        }
      ]
    },
    {
      "model": "Land",
      "trim": "Cruiser Base",
      "tires": [
        {
          "size": "265/60R20"
        },
        {
          "size": "265/70R18"
        }
      ]
    },
    {
      "model": "Mirai",
      "trim": "XLE",
      "tires": [
        {
          "size": "235/55R19"
        }
      ]
    },
    {
      "model": "Prius",
      "trim": "AWD-e Limited",
      "tires": [
        {
          "size": "195/50R19"
        }
      ]
    },
    {
      "model": "Prius",
      "trim": "AWD-e XLE",
      "tires": [
        {
          "size": "195/50R19"
        }
      ]
    },
    {
      "model": "Prius",
      "trim": "Plug-In Hybrid SE",
      "tires": [
        {
          "size": "195/60R17"
        }
      ]
    },
    {
      "model": "Prius",
      "trim": "Plug-In Hybrid XSE",
      "tires": [
        {
          "size": "195/50R19"
        }
      ]
    },
    {
      "model": "Prius",
      "trim": "Plug-In Hybrid XSE Premium",
      "tires": [
        {
          "size": "195/50R19"
        }
      ]
    },
    {
      "model": "RAV4",
      "trim": "Hybrid LE",
      "tires": [
        {
          "size": "225/65R17"
        }
      ]
    },
    {
      "model": "RAV4",
      "trim": "Hybrid Limited",
      "tires": [
        {
          "size": "225/60R18"
        }
      ]
    },
    {
      "model": "RAV4",
      "trim": "Hybrid SE",
      "tires": [
        {
          "size": "225/60R18"
        }
      ]
    },
    {
      "model": "RAV4",
      "trim": "Hybrid Woodland Edition",
      "tires": [
        {
          "size": "225/60R18"
        }
      ]
    },
    {
      "model": "RAV4",
      "trim": "Hybrid XLE",
      "tires": [
        {
          "size": "225/65R17"
        }
      ]
    },
    {
      "model": "RAV4",
      "trim": "Hybrid XLE Premium",
      "tires": [
        {
          "size": "225/60R18"
        }
      ]
    },
    {
      "model": "RAV4",
      "trim": "Hybrid XSE",
      "tires": [
        {
          "size": "225/60R18"
        }
      ]
    },
    {
      "model": "RAV4",
      "trim": "LE (AWD)",
      "tires": [
        {
          "size": "225/65R17"
        }
      ]
    },
    {
      "model": "RAV4",
      "trim": "Limited (AWD)",
      "tires": [
        {
          "size": "235/55R19"
        }
      ]
    },
    {
      "model": "RAV4",
      "trim": "XLE (AWD)",
      "tires": [
        {
          "size": "225/65R17"
        }
      ]
    },
    {
      "model": "RAV4",
      "trim": "XLE Premium (AWD)",
      "tires": [
        {
          "size": "235/55R19"
        }
      ]
    },
    {
      "model": "Sequoia",
      "trim": "Capstone",
      "tires": [
        {
          "size": "265/50R22"
        }
      ]
    },
    {
      "model": "Sequoia",
      "trim": "Limited",
      "tires": [
        {
          "size": "265/60R20"
        }
      ]
    },
    {
      "model": "Sequoia",
      "trim": "Limited w/TRD Pro pkg.",
      "tires": [
        {
          "size": "285/65R18"
        }
      ]
    },
    {
      "model": "Sequoia",
      "trim": "Platinum",
      "tires": [
        {
          "size": "265/60R20"
        }
      ]
    },
    {
      "model": "Sequoia",
      "trim": "TRD Off Road",
      "tires": [
        {
          "size": "265/70R18"
        }
      ]
    },
    {
      "model": "Sequoia",
      "trim": "TRD Pro",
      "tires": [
        {
          "size": "285/65R18"
        }
      ]
    },
    {
      "model": "Sienna",
      "trim": "LE",
      "tires": [
        {
          "size": "P235/65R17"
        }
      ]
    },
    {
      "model": "Sienna",
      "trim": "Limited",
      "tires": [
        {
          "size": "P235/60R18"
        }
      ]
    },
    {
      "model": "Sienna",
      "trim": "XLE",
      "tires": [
        {
          "size": "P235/65R17"
        }
      ]
    },
    {
      "model": "Sienna",
      "trim": "XSE (AWD)",
      "tires": [
        {
          "size": "P235/60R18"
        }
      ]
    },
    {
      "model": "Sienna",
      "trim": "XSE (FWD)",
      "tires": [
        {
          "size": "235/50R20"
        }
      ]
    },
    {
      "model": "Tacoma",
      "trim": "Limited",
      "tires": [
        {
          "size": "265/65R18"
        }
      ]
    },
    {
      "model": "Tacoma",
      "trim": "SR5",
      "tires": [
        {
          "size": "245/70R17"
        }
      ]
    },
    {
      "model": "Tacoma",
      "trim": "TRD Off-Road Gas",
      "tires": [
        {
          "size": "265/70R17"
        }
      ]
    },
    {
      "model": "Tacoma",
      "trim": "TRD Off-Road Premium Gas",
      "tires": [
        {
          "size": "265/70R17"
        }
      ]
    },
    {
      "model": "Tacoma",
      "trim": "TRD Off-Road Premium Hybrid",
      "tires": [
        {
          "size": "265/70R18"
        }
      ]
    },
    {
      "model": "Tacoma",
      "trim": "TRD Pro",
      "tires": [
        {
          "size": "265/70R18"
        }
      ]
    },
    {
      "model": "Tacoma",
      "trim": "TRD Sport",
      "tires": [
        {
          "size": "265/65R18"
        }
      ]
    },
    {
      "model": "Tacoma",
      "trim": "TRD Sport +",
      "tires": [
        {
          "size": "265/65R18"
        }
      ]
    },
    {
      "model": "Tacoma",
      "trim": "TRD Sport + 6MT",
      "tires": [
        {
          "size": "265/65R18"
        },
        {
          "size": "265/70R17"
        }
      ]
    },
    {
      "model": "Tacoma",
      "trim": "Trailhunter",
      "tires": [
        {
          "size": "265/70R18"
        }
      ]
    },
    {
      "model": "Tundra",
      "trim": "1794 Edition",
      "tires": [
        {
          "size": "265/60R20"
        }
      ]
    },
    {
      "model": "Tundra",
      "trim": "1794 Edition (8.5J Rims)",
      "tires": [
        {
          "size": "265/60R20"
        }
      ]
    },
    {
      "model": "Tundra",
      "trim": "Capstone",
      "tires": [
        {
          "size": "265/50R22"
        }
      ]
    },
    {
      "model": "Tundra",
      "trim": "Limited",
      "tires": [
        {
          "size": "265/60R20"
        }
      ]
    },
    {
      "model": "Tundra",
      "trim": "Limited w/TRD Off-Road Pkg.",
      "tires": [
        {
          "size": "265/60R20"
        }
      ]
    },
    {
      "model": "Tundra",
      "trim": "Platinum",
      "tires": [
        {
          "size": "265/60R20"
        }
      ]
    },
    {
      "model": "Tundra",
      "trim": "SR w/steel wheels",
      "tires": [
        {
          "size": "245/75R18"
        }
      ]
    },
    {
      "model": "Tundra",
      "trim": "SR5",
      "tires": [
        {
          "size": "265/70R18"
        }
      ]
    },
    {
      "model": "Tundra",
      "trim": "SR5 w/20 Inch TRD Pkg.",
      "tires": [
        {
          "size": "265/60R20"
        }
      ]
    },
    {
      "model": "Tundra",
      "trim": "TRD Pro",
      "tires": [
        {
          "size": "285/65R18"
        }
      ]
    },
    {
      "model": "bZ4X",
      "trim": "LE",
      "tires": [
        {
          "size": "235/60R18"
        }
      ]
    },
    {
      "model": "bZ4X",
      "trim": "XLE",
      "tires": [
        {
          "size": "235/60R18"
        }
      ]
    },
    {
      "model": "bZ4X",
      "trim": "XLE w/Technology Pkg.",
      "tires": [
        {
          "size": "235/50R20"
        }
      ]
    }
  ],
  "metadata": {
    "scraping_date": "2025-06-21T12:41:13.818284",
    "total_vehicles": 102,
    "total_tire_sizes": 39,
    "migration_date": "2025-06-23T14:37:31.505369",
    "migrated_to_new_format": true
  }
}